{
  "parent": "minecraft:recipes/root",
  "criteria": {
    "has_item": {
      "conditions": {
        "items": [
          {
            "items": "improved-crystals:prismarine_crystal_block"
          }
        ]
      },
      "trigger": "minecraft:inventory_changed"
    },
    "requirements": [
      [
        "has_item"
      ]
    ],
    "rewards": {
      "recipes": [
        "improved-crystals:polished_prismarine_crystals",
        "improved-crystals:polished_prismarine_crystals_from_stonecutter"
      ]
    }
  }
}